{
	"input": {
		"method": "POST",
		"url": "{{pre.eatojoy_url}}",
		"rest": "/admin/push/create",
		"headers":{"Content-Type": "application/json",
               "eatojoy-admin-api-key":"{{pre.eatojoy_bk_token}}"
		},
		"param": {
			"receiver":2,
            "title":"推送标题",
            "content":"推送内容",
			"type":1,
			"url":"https://www.hk01.com/article/273559/"

		}
	},
	"output": {
		"data": {
			"TYPE": "int"
		},
		"code": {
			"EQ": 0
		},
		"status": {
			"EQ": true
		},
		"message": {
			"EQ": "success"
		}
	},"sleep":5
}
