{
        "input": {
                "method": "get",
                "url": "{{pre.rizili_woa_url}}",
                "rest": "/helper/token/token",
                "headers": {},
                "param": [
                        {
                                "name": "uc_id",
                                "in": "formData",
                                "description": "用户UCID（优先级一）",
                                "required": false,
                                "type": "integer"
                        },
                        {
                                "name": "mobile",
                                "in": "formData",
                                "description": "手机号码（优先级二）",
                                "required": false,
                                "type": "integer"
                        },
                        {
                                "name": "token",
                                "in": "formData",
                                "description": "登陆token,不填写则默认为UCID或手机号码",
                                "required": false,
                                "type": "integer"
                        }
                ]
        },
        "output": {
                "code": 0,
                "message": {
                        "EQ": ""
                },
                "status": true,
                "data": {
                        "type": "dict"
                }
        }
}