{
        "input": {
                "method": "post",
                "url": "{{pre.erp_url}}",
                "rest": "/index/index/out",
                "headers": {
                        "token": ""
                },
                "param": []
        },
        "output": {
                "code": 0,
                "message": {
                        "EQ": ""
                },
                "status": true,
                "data": {
                        "type": "dict"
                }
        }
}